{
  "PFE": {
    "prediction": 0.8834909106736261,
    "regime": "downtrend",
    "price": 25.329999923706055,
    "sentiment": 0.15593691703701473,
    "sector": "Healthcare",
    "signal": "AVOID",
    "combined": 0.5312819298115785
  },
  "RIVN": {
    "prediction": 0.791334386693775,
    "regime": "downtrend",
    "price": 13.350000381469727,
    "sentiment": -0.013683124285723483,
    "sector": "Consumer",
    "signal": "AVOID",
    "combined": 0.44206400715912025
  },
  "MRK": {
    "prediction": 0.747914859251501,
    "regime": "downtrend",
    "price": 112.55999755859375,
    "sentiment": 0.1751279763993807,
    "sector": "Healthcare",
    "signal": "AVOID",
    "combined": 0.45377451083077674
  },
  "XOM": {
    "prediction": 0.7380185931384752,
    "regime": "sideways",
    "price": 160.49000549316406,
    "sentiment": 0.1995387366300242,
    "sector": "Energy",
    "signal": "HOLD",
    "combined": 0.54271890320909
  },
  "NET": {
    "prediction": 0.7324798423437949,
    "regime": "sideways",
    "price": 201.75,
    "sentiment": 0.07454560453900033,
    "sector": "Technology",
    "signal": "HOLD",
    "combined": 0.514397026314077
  },
  "MCD": {
    "prediction": 0.6982516245688837,
    "regime": "downtrend",
    "price": 282.4700012207031,
    "sentiment": -0.16237981440499424,
    "sector": "Consumer",
    "signal": "AVOID",
    "combined": 0.3564750118603313
  },
  "JNJ": {
    "prediction": 0.6729820057241142,
    "regime": "downtrend",
    "price": 228.9199981689453,
    "sentiment": 0.08276611829974821,
    "sector": "Healthcare",
    "signal": "AVOID",
    "combined": 0.39034242709441813
  },
  "HD": {
    "prediction": 0.6558075054648813,
    "regime": "downtrend",
    "price": 299.80999755859375,
    "sentiment": 0.0,
    "sector": "Consumer",
    "signal": "AVOID",
    "combined": 0.36348450327892873
  },
  "META": {
    "prediction": 0.6164364794043395,
    "regime": "sideways",
    "price": 611.2100219726562,
    "sentiment": 0.0,
    "sector": "Communications",
    "signal": "HOLD",
    "combined": 0.3698618876426037
  },
  "MS": {
    "prediction": 0.5517821352282042,
    "regime": "uptrend",
    "price": 192.69000244140625,
    "sentiment": 0.0,
    "sector": "Financials",
    "signal": "VETOED",
    "combined": 0.3310692811369225
  },
  "ABBV": {
    "prediction": 0.5477549969708031,
    "regime": "downtrend",
    "price": 209.41000366210938,
    "sentiment": 0.0,
    "sector": "Healthcare",
    "signal": "AVOID",
    "combined": 0.2986529981824818
  },
  "BAC": {
    "prediction": 0.5355485032276727,
    "regime": "uptrend",
    "price": 50.689998626708984,
    "sentiment": 0.0,
    "sector": "Financials",
    "signal": "HOLD",
    "combined": 0.3213291019366036
  },
  "OXY": {
    "prediction": 0.5344475640865961,
    "regime": "uptrend",
    "price": 59.70000076293945,
    "sentiment": 0.0,
    "sector": "Energy",
    "signal": "HOLD",
    "combined": 0.38066853845195764
  },
  "LLY": {
    "prediction": 0.529959899200954,
    "regime": "sideways",
    "price": 988.0900268554688,
    "sentiment": 0.0,
    "sector": "Healthcare",
    "signal": "HOLD",
    "combined": 0.2879759395205724
  },
  "SPY": {
    "prediction": 0.5237288624359229,
    "regime": "uptrend",
    "price": 738.6500244140625,
    "sentiment": 0.0,
    "sector": "Market",
    "signal": "HOLD",
    "combined": 0.3142373174615537
  },
  "IWM": {
    "prediction": 0.5171426241123964,
    "regime": "uptrend",
    "price": 275.9700012207031,
    "sentiment": 0.0,
    "sector": "Market",
    "signal": "HOLD",
    "combined": 0.3102855744674378
  },
  "PLTR": {
    "prediction": 0.5165944646113614,
    "regime": "downtrend",
    "price": 135.13999938964844,
    "sentiment": 0.0,
    "sector": "Technology",
    "signal": "AVOID",
    "combined": 0.3699566787668168
  },
  "UNH": {
    "prediction": 0.48744534222120856,
    "regime": "uptrend",
    "price": 391.1300048828125,
    "sentiment": 0.0,
    "sector": "Healthcare",
    "signal": "HOLD",
    "combined": 0.2624672053327251
  },
  "CRWD": {
    "prediction": 0.47472033934732144,
    "regime": "uptrend",
    "price": 618.8300170898438,
    "sentiment": 0.0,
    "sector": "Technology",
    "signal": "HOLD",
    "combined": 0.34483220360839284
  },
  "GS": {
    "prediction": 0.46641329954634986,
    "regime": "uptrend",
    "price": 946.3599853515625,
    "sentiment": 0.0,
    "sector": "Financials",
    "signal": "HOLD",
    "combined": 0.2798479797278099
  },
  "NFLX": {
    "prediction": 0.46320206977702916,
    "regime": "downtrend",
    "price": 89.6500015258789,
    "sentiment": 0.0,
    "sector": "Communications",
    "signal": "AVOID",
    "combined": 0.27792124186621747
  },
  "CVX": {
    "prediction": 0.4622056137118493,
    "regime": "sideways",
    "price": 196.1199951171875,
    "sentiment": 0.0,
    "sector": "Energy",
    "signal": "HOLD",
    "combined": 0.33732336822710957
  },
  "SOFI": {
    "prediction": 0.45142168619196976,
    "regime": "downtrend",
    "price": 15.710000038146973,
    "sentiment": 0.0,
    "sector": "Financials",
    "signal": "AVOID",
    "combined": 0.27085301171518184
  },
  "QQQ": {
    "prediction": 0.4355423540811784,
    "regime": "uptrend",
    "price": 705.8800048828125,
    "sentiment": 0.0,
    "sector": "Technology",
    "signal": "HOLD",
    "combined": 0.32132541244870705
  },
  "JPM": {
    "prediction": 0.41052056208794063,
    "regime": "uptrend",
    "price": 300.7300109863281,
    "sentiment": 0.0,
    "sector": "Financials",
    "signal": "HOLD",
    "combined": 0.24631233725276436
  },
  "NVDA": {
    "prediction": 0.4063576939509722,
    "regime": "uptrend",
    "price": 222.32000732421875,
    "sentiment": 0.0,
    "sector": "Technology",
    "signal": "HOLD",
    "combined": 0.3038146163705833
  },
  "TSLA": {
    "prediction": 0.3740261269615029,
    "regime": "uptrend",
    "price": 409.989990234375,
    "sentiment": 0.0,
    "sector": "Consumer",
    "signal": "HOLD",
    "combined": 0.19441567617690172
  },
  "CRM": {
    "prediction": 0.3651646886342101,
    "regime": "downtrend",
    "price": 179.47999572753906,
    "sentiment": 0.0,
    "sector": "Technology",
    "signal": "AVOID",
    "combined": 0.27909881318052604
  },
  "DIA": {
    "prediction": 0.3469791591223427,
    "regime": "uptrend",
    "price": 497.010009765625,
    "sentiment": 0.0,
    "sector": "Market",
    "signal": "HOLD",
    "combined": 0.2081874954734056
  },
  "WMT": {
    "prediction": 0.34625054577239683,
    "regime": "uptrend",
    "price": 133.33999633789062,
    "sentiment": 0.0,
    "sector": "Staples",
    "signal": "HOLD",
    "combined": 0.2077503274634381
  },
  "HOOD": {
    "prediction": 0.34479550579643636,
    "regime": "uptrend",
    "price": 77.1500015258789,
    "sentiment": 0.0,
    "sector": "Financials",
    "signal": "HOLD",
    "combined": 0.20687730347786182
  },
  "AMD": {
    "prediction": 0.3364951571728053,
    "regime": "volatile",
    "price": 420.989990234375,
    "sentiment": 0.0,
    "sector": "Technology",
    "signal": "CAUTION",
    "combined": 0.2618970943036832
  },
  "GOOGL": {
    "prediction": 0.32206129873646316,
    "regime": "uptrend",
    "price": 396.94000244140625,
    "sentiment": 0.0,
    "sector": "Technology",
    "signal": "HOLD",
    "combined": 0.25323677924187793
  },
  "DDOG": {
    "prediction": 0.3193943774568554,
    "regime": "volatile",
    "price": 208.82000732421875,
    "sentiment": 0.0,
    "sector": "Technology",
    "signal": "CAUTION",
    "combined": 0.2516366264741132
  },
  "MSFT": {
    "prediction": 0.2933863945503959,
    "regime": "uptrend",
    "price": 423.5400085449219,
    "sentiment": 0.0,
    "sector": "Technology",
    "signal": "HOLD",
    "combined": 0.23603183673023753
  },
  "AAPL": {
    "prediction": 0.24621034008709455,
    "regime": "uptrend",
    "price": 297.8399963378906,
    "sentiment": 0.0,
    "sector": "Technology",
    "signal": "HOLD",
    "combined": 0.20772620405225672
  },
  "AMZN": {
    "prediction": 0.2404657435475363,
    "regime": "uptrend",
    "price": 264.8599853515625,
    "sentiment": 0.0,
    "sector": "Consumer",
    "signal": "HOLD",
    "combined": 0.11427944612852178
  },
  "V": {
    "prediction": 0.21772991010303167,
    "regime": "uptrend",
    "price": 332.6400146484375,
    "sentiment": 0.0,
    "sector": "Financials",
    "signal": "HOLD",
    "combined": 0.130637946061819
  },
  "COST": {
    "prediction": 0.2082569680939422,
    "regime": "uptrend",
    "price": 1076.469970703125,
    "sentiment": 0.0,
    "sector": "Consumer",
    "signal": "HOLD",
    "combined": 0.09495418085636531
  },
  "SNOW": {
    "prediction": 0.19539526287404785,
    "regime": "sideways",
    "price": 164.24000549316406,
    "sentiment": 0.0,
    "sector": "Technology",
    "signal": "HOLD",
    "combined": 0.17723715772442872
  },
  "MARA": {
    "prediction": 0.1447234186547829,
    "regime": "uptrend",
    "price": 12.180000305175781,
    "sentiment": 0.0,
    "sector": "Technology",
    "signal": "HOLD",
    "combined": 0.14683405119286974
  }
}